[
  {
    "id": "ThreeCupChicken",
    "name": "三杯雞",
    "amount": "四人份",
    "ingredients": [
      ["chickenLeg", "4"],
      ["gingerSlice", "10"],
      ["garlic", "10"],
      ["sesameOil", "120"],
      ["sugar", "2"],
      ["soySauce", "120"],
      ["riceWine", "120"],
      ["basil", "1"]
    ],
    "steps": [
      "1.將雞腿剁小塊.",
      "2.鍋中倒入麻油, 以小火將薑片爆至金黃. 將雞腿加入, 以大火將雞腿翻炒至變色.",
      "3.蒜頭和糖加入翻炒均勻, 倒入醬油和米酒以大火煮滾. 蓋上鍋蓋, 悶至湯汁微微收乾變的較為濃稠 (約10 分鐘).",
      "4.加入九層塔翻炒, 再嗆入一大匙米酒即可起鍋."
    ],
    "image": "https://imageproxy.icook.network/resize?background=255%2C255%2C255&nocrop=true&stripmeta=true&type=auto&url=http%3A%2F%2Ftokyo-kitchen.icook.tw.s3.amazonaws.com%2Fuploads%2Frecipe%2Fcover%2F161587%2F83ca1ec22fa5895c.jpg&width=1242"
  },
  {
    "id": "preservedRadishomelette",
    "name": "菜脯蛋",
    "ingredients": [
      ["egg", "3"],
      ["scallion", "1"],
      ["driedRadish", "25"],
      ["salt", "1"],
      ["pepper", "1"],
      ["bonitoSauce", "1"]
    ],
    "steps": [
      "1.菜脯用清水搓揉洗乾淨，壓乾水分切末，蔥切成蔥花。蛋和蔥花混合，加入鹽、鰹魚醬油、胡椒粉，攪拌均勻備用。",
      "2.乾鍋（不放油）下菜脯末炒香",
      "3.炒香的菜脯加入蔥蛋液中，攪拌均勻，下一大匙油，油熱後把蛋液下下去。",
      "4.兩面煎焦香後就可以起鍋了。"
    ],
    "image": "https://tokyo-kitchen.icook.network/uploads/recipe/cover/328980/f591b7fd14dbdf8c.jpg"
  },
  {
    "id": "chickenGarlicSoup",
    "name": "蒜頭香菇幾湯",
    "ingredients": [
      ["chickenLeg", "2"],
      ["driedShiitake", "10"],
      ["garlic", "10"]
    ],
    "steps": [
        "1.乾香菇洗淨後用300cc熱開水浸泡，軟化後撈起擠乾備用，香菇水留下來運用。",
        "2.中火熱油鍋將蒜頭爆香至略為金黃後立馬撈起備用。",
        "3.將撈起的蒜頭浸泡香菇水。",
        "4.將剛爆香完的蒜頭油，再次爆香香菇，這二樣都中小火爆即可，食材味道才不會因爆香過烈可惜了。",
        "5.雞腿肉要先以熱開水汆燙後放入略為拌炒至熱氣上升後，加入步驟三的蒜頭香菇水，再加入熱開水準備燉煮，您可移至電鍋以一杯水外鍋燉，或是如我的作法用湯鍋小火悶燉。",
        "6.湯頭要好喝就是過程都不要好奇去開鍋:joy:把握好時間及中小火慢燉就對了，燉上約30分後，開鍋調味就行囉。"
    ],
    "image": "https://tokyo-kitchen.icook.network/uploads/recipe/cover/328980/f591b7fd14dbdf8c.jpg"
  }
]
